Metadata-Version: 2.1
Name: trackdir
Version: 1.0.0
Summary: A package to track file changes in a directory
Home-page: https://github.com/bytebreach/trackdir
Author: MrFidal
Author-email: mrfidal@proton.me
Classifier: Programming Language :: Python :: 3
Classifier: License :: OSI Approved :: MIT License
Classifier: Operating System :: OS Independent
Requires-Python: >=3.6
License-File: LICENSE
